cvxpy_gurobi/__init__.py
cvxpy_gurobi/_version.py
cvxpy_gurobi/interface.py
cvxpy_gurobi/py.typed
cvxpy_gurobi/translation.py
cvxpy_gurobi-1.2.0.dist-info/METADATA
cvxpy_gurobi-1.2.0.dist-info/WHEEL
cvxpy_gurobi-1.2.0.dist-info/licenses/LICENSE
cvxpy_gurobi-1.2.0.dist-info/RECORD
