Metadata-Version: 2.4
Name: cvxpy-gurobi
Version: 1.2.0
Summary: Translate CVXPY problems into gurobipy models
Project-URL: Documentation, https://github.com/jonathanberthias/cvxpy-gurobi#readme
Project-URL: Issues, https://github.com/jonathanberthias/cvxpy-gurobi/issues
Project-URL: Source, https://github.com/jonathanberthias/cvxpy-gurobi
Author-email: Jonathan Berthias <jvberthias@gmail.com>
License-Expression: Apache-2.0
License-File: LICENSE
Keywords: cvxpy,gurobi,gurobipy,optimization
Classifier: Development Status :: 4 - Beta
Classifier: Intended Audience :: Science/Research
Classifier: License :: OSI Approved :: Apache Software License
Classifier: Programming Language :: Python
Classifier: Programming Language :: Python :: 3 :: Only
Classifier: Programming Language :: Python :: 3.8
Classifier: Programming Language :: Python :: 3.9
Classifier: Programming Language :: Python :: 3.10
Classifier: Programming Language :: Python :: 3.11
Classifier: Programming Language :: Python :: 3.12
Classifier: Programming Language :: Python :: 3.13
Classifier: Programming Language :: Python :: Implementation :: CPython
Classifier: Topic :: Scientific/Engineering :: Mathematics
Requires-Python: >=3.8
Requires-Dist: gurobipy
Requires-Dist: numpy>=1.23.0
Requires-Dist: scipy>=1.4.0
